secedgar/__init__.py
secedgar/cik_lookup.py
secedgar/cli.py
secedgar/client.py
secedgar/exceptions.py
secedgar/parser.py
secedgar/utils.py
secedgar/core/__init__.py
secedgar/core/_base.py
secedgar/core/_index.py
secedgar/core/combo.py
secedgar/core/company.py
secedgar/core/daily.py
secedgar/core/filing_types.py
secedgar/core/filings.py
secedgar/core/quarterly.py
secedgar/core/rest.py
secedgar/tests/__init__.py
secedgar/tests/conftest.py
secedgar/tests/test_cik_lookup.py
secedgar/tests/test_cli.py
secedgar/tests/test_client.py
secedgar/tests/test_exceptions.py
secedgar/tests/test_parser.py
secedgar/tests/test_utils.py
secedgar/tests/utils.py
secedgar/tests/core/__init__.py
secedgar/tests/core/test_combo.py
secedgar/tests/core/test_company.py
secedgar/tests/core/test_daily.py
secedgar/tests/core/test_filings.py
secedgar/tests/core/test_quarterly.py
secedgar/tests/core/test_rest.py
secedgar-0.5.0.dist-info/LICENSE
secedgar-0.5.0.dist-info/METADATA
secedgar-0.5.0.dist-info/WHEEL
secedgar-0.5.0.dist-info/entry_points.txt
secedgar-0.5.0.dist-info/top_level.txt
secedgar-0.5.0.dist-info/RECORD
