Metadata-Version: 2.1
Name: secedgar
Version: 0.5.0
Summary: SEC-Edgar implements a basic crawler for downloading
Home-page: https://github.com/sec-edgar/sec-edgar
Download-URL: https://github.com/sec-edgar/sec-edgar/releases
Author: Rahul Ranjan
Author-email: rahul.rrixe@gmail.com
Maintainer: Jack Moody
Maintainer-email: jacklaytonmoody@gmail.com
License: Apache License (2.0)
Keywords: SEC,EDGAR,crawler,filings
Classifier: Programming Language :: Python :: 3.6
Classifier: Programming Language :: Python :: 3.7
Classifier: Programming Language :: Python :: 3.8
Classifier: Programming Language :: Python :: 3.9
Classifier: Environment :: Console
Classifier: License :: OSI Approved :: Apache Software License
Classifier: Operating System :: OS Independent
Classifier: Programming Language :: Python
Classifier: Topic :: Software Development :: Libraries :: Python Modules
License-File: LICENSE
Requires-Dist: beautifulsoup4
Requires-Dist: aiohttp
Requires-Dist: async-timeout (<4.0,>=3.0)
Requires-Dist: urllib3
Requires-Dist: requests
Requires-Dist: lxml
Requires-Dist: tqdm
Requires-Dist: typing-extensions (<4.2.0) ; python_version == "3.6"
Provides-Extra: cli
Requires-Dist: beautifulsoup4 ; extra == 'cli'
Requires-Dist: aiohttp ; extra == 'cli'
Requires-Dist: async-timeout (<4.0,>=3.0) ; extra == 'cli'
Requires-Dist: urllib3 ; extra == 'cli'
Requires-Dist: requests ; extra == 'cli'
Requires-Dist: lxml ; extra == 'cli'
Requires-Dist: tqdm ; extra == 'cli'
Requires-Dist: Click ; extra == 'cli'
